geogis/__init__.py
geogis/_const.py
geogis/boundary.py
geogis/gee_export.py
geogis/map_calc.py
geogis/mask.py
geogis/projection.py
geogis/ras_to_shp.py
geogis/raster.py
geogis/shape.py
geogis/shp_to_ras.py
geogis/spatial_calc.py
geogis/utils.py
geogis/zonal_stats.py
geogis-0.0.1.dist-info/LICENSE
geogis-0.0.1.dist-info/METADATA
geogis-0.0.1.dist-info/WHEEL
geogis-0.0.1.dist-info/top_level.txt
geogis-0.0.1.dist-info/RECORD
