Metadata-Version: 2.1
Name: geogis
Version: 0.0.1
Summary: GIS tools based on GDAL
Home-page: https://github.com/xiejx5/geogis
Author: Cody James
Author-email: xiejx5@gmail.com
License: MIT
Classifier: License :: OSI Approved :: MIT License
Classifier: Programming Language :: Python
Classifier: Programming Language :: Python :: 3
Classifier: Programming Language :: Python :: 3.6
Classifier: Programming Language :: Python :: Implementation :: CPython
Classifier: Programming Language :: Python :: Implementation :: PyPy
Requires-Python: >=3.6.0
License-File: LICENSE
Requires-Dist: numpy
Requires-Dist: gdal
Requires-Dist: tqdm
Provides-Extra: fancy_feature
Requires-Dist: pandas ; extra == 'fancy_feature'
Requires-Dist: requests ; extra == 'fancy_feature'
Requires-Dist: earthengine-api ; extra == 'fancy_feature'
